setup.cfg
setup.py
often_things/__init__.py
often_things/arcade_tools.py
often_things.egg-info/PKG-INFO
often_things.egg-info/SOURCES.txt
often_things.egg-info/dependency_links.txt
often_things.egg-info/requires.txt
often_things.egg-info/top_level.txt