Metadata-Version: 2.1
Name: often-things
Version: 0.0.2
Summary: This is the module helping you to avoid writing same code many times.
Author: Sebby_child_developer
Author-email: sebbyrogers20@gmail.com
Requires-Python: >=3.6
